enigmacrypt/__init__.py
enigmacrypt-0.0.8.dist-info/LICENSE
enigmacrypt-0.0.8.dist-info/METADATA
enigmacrypt-0.0.8.dist-info/WHEEL
enigmacrypt-0.0.8.dist-info/top_level.txt
enigmacrypt-0.0.8.dist-info/RECORD
