Metadata-Version: 2.1
Name: enigmacrypt
Version: 0.0.8
Summary: Encoding and decoding strings using keys
Home-page: https://github.com/Wooks08/EnigmaCrypt
Author: WooksCode (Wojciech Karwowski)
Author-email: <wookscode.kontakt@gmail.com>
License: MIT
Keywords: python,encode,decode,decoder,encoder,string encryption,string decryption
Platform: UNKNOWN
Classifier: Development Status :: 3 - Alpha
Classifier: Intended Audience :: Developers
Classifier: Programming Language :: Python :: 3
Classifier: Operating System :: Unix
Classifier: Operating System :: MacOS :: MacOS X
Classifier: Operating System :: Microsoft :: Windows
Requires-Python: >=3.07
License-File: LICENSE
Provides-Extra: dev
Requires-Dist: pytest (>=7.0) ; extra == 'dev'
Requires-Dist: twine (>=4.0.2) ; extra == 'dev'
